Metadata-Version: 2.1
Name: covpipe
Version: 3.1.0
Summary: Sars-Cov-2 NGS Pipline for generating consensus sequences
Home-page: https://gitlab.com/RKIBioinformaticsPipelines/ncov_minipipe
Author: Oliver Drechsel, Stephan Fuchs, Martin Hölzer, René Kmiecinski
Author-email: r.w.kmiecinski@gmail.com
License: GPLv3
Platform: UNKNOWN
Classifier: Programming Language :: Python :: 3
Classifier: Programming Language :: Python :: 3.6
Classifier: Intended Audience :: Science/Research
Classifier: License :: OSI Approved :: GNU General Public License v3 (GPLv3)
Classifier: Topic :: Scientific/Engineering :: Bio-Informatics
Requires-Dist: snakemake (<7,>5.26)
Requires-Dist: strictyaml
Requires-Dist: PyYAML
Requires-Dist: biopython
Requires-Dist: pysam
Requires-Dist: pandas
Requires-Dist: numpy
